{"version":1,"resource":"file:///home/monteiro/codes/portifolio/src/sections/NewProjects.tsx","entries":[{"id":"gsef.tsx","timestamp":1755453966486},{"id":"RZTs.tsx","timestamp":1755453984669},{"id":"3ELO.tsx","timestamp":1755454016589},{"id":"YFZB.tsx","timestamp":1755475803221},{"id":"P9Br.tsx","timestamp":1755475827865},{"id":"FIA0.tsx","timestamp":1755475844203},{"id":"QbgR.tsx","timestamp":1755475866162},{"id":"oNO1.tsx","timestamp":1755475909531},{"id":"E0OQ.tsx","timestamp":1755475921342},{"id":"zg1U.tsx","timestamp":1755475940965},{"id":"lmTY.tsx","timestamp":1755475955847},{"id":"xWDz.tsx","timestamp":1755476006858},{"id":"mav7.tsx","timestamp":1755476032103},{"id":"EXnW.tsx","timestamp":1755476058498},{"id":"bwH2.tsx","timestamp":1755476098129},{"id":"6xB8.tsx","timestamp":1755476130857},{"id":"IQ68.tsx","timestamp":1755476149118},{"id":"9AMy.tsx","timestamp":1755476204642},{"id":"On21.tsx","timestamp":1755476264178},{"id":"N65G.tsx","timestamp":1755476278187},{"id":"9xGB.tsx","timestamp":1755476296744},{"id":"tUXf.tsx","timestamp":1755476321854},{"id":"85hs.tsx","timestamp":1755476333802},{"id":"lBaf.tsx","timestamp":1755476352799},{"id":"hnvY.tsx","timestamp":1755476370058},{"id":"u6Uk.tsx","timestamp":1755476397339},{"id":"JWds.tsx","timestamp":1755476483625},{"id":"EUqq.tsx","timestamp":1755476517780},{"id":"9HbV.tsx","timestamp":1755476540979},{"id":"NpSq.tsx","source":"undoRedo.source","timestamp":1755476556517},{"id":"DcFU.tsx","timestamp":1755476564287},{"id":"zTuG.tsx","timestamp":1755476605414},{"id":"J48f.tsx","timestamp":1755476636185},{"id":"65nD.tsx","timestamp":1755476653851},{"id":"15s4.tsx","timestamp":1755476718191},{"id":"AkAa.tsx","timestamp":1755476734504},{"id":"LIJf.tsx","timestamp":1755536181912},{"id":"kUsv.tsx","timestamp":1755614923562},{"id":"sh0z.tsx","timestamp":1755649292362},{"id":"kHaL.tsx","timestamp":1755649416771},{"id":"pc1h.tsx","source":"undoRedo.source","timestamp":1755649433324},{"id":"PfPW.tsx","timestamp":1755649947600},{"id":"BRE0.tsx","timestamp":1755649986764},{"id":"q3ZH.tsx","timestamp":1755650029879},{"id":"Ezoe.tsx","timestamp":1755650048524},{"id":"GWGI.tsx","source":"undoRedo.source","timestamp":1755650065699},{"id":"52Oc.tsx","timestamp":1755650118802},{"id":"CFNw.tsx","timestamp":1755650145122},{"id":"yhgj.tsx","timestamp":1755802086313},{"id":"zg81.tsx","timestamp":1755802101212}]}