{"version":1,"resource":"file:///home/monteiro/codes/dashboards-thera/src/hooks/useFirebase.ts","entries":[{"id":"g2Kg.ts","source":"Chat Edit: '@agent Continue: \"Continue to iterate?\"'","timestamp":1758674177252},{"id":"hgDQ.ts","source":"Chat Edit: 'faz um npm run build pra corrigir os erros'","timestamp":1758674556149},{"id":"b9ne.ts","timestamp":1758674858812},{"id":"gZdl.ts","timestamp":1758674869296},{"id":"kgsW.ts","timestamp":1758674890110},{"id":"ml2T.ts","timestamp":1758714952365},{"id":"NaLh.ts","source":"Chat Edit: '@agent Continue: \"Continue to iterate?\"'","timestamp":1758718665133},{"id":"ZDSw.ts","source":"Chat Edit: '@agent Continue: \"Continue to iterate?\"'","timestamp":1758718678944},{"id":"T9qv.ts","source":"Chat Edit: '@agent Continue: \"Continue to iterate?\"'","timestamp":1758718690444},{"id":"QSeQ.ts","source":"Chat Edit: 'efetue'","timestamp":1759603869933}]}