{"version":1,"resource":"file:///home/monteiro/codes/revis/app/acesso-negado/page.tsx","entries":[{"id":"G6cH.tsx","source":"Chat Edit: 'Agora vamos para os proximos passos, conforme for sendo concluido marque nesse markdown como concluido'","timestamp":1762723960937},{"id":"xVrq.tsx","source":"Chat Edit: 'Seguinte, apenas ajuste tudo de acordo com o Design já definindo antes, inclusive ajustando as paginas que não tem a sidebar, alguns estilos estão estranho, e alguns modais estão fora de contexto. Falta UX melhorada e as respostas já definidas antes'","timestamp":1762732095298},{"id":"gMES.tsx","timestamp":1762738900695}]}