{"version":1,"resource":"file:///home/monteiro/codes/main-thera/src/components/Background.tsx","entries":[{"id":"mxzX.tsx","timestamp":1754180458259},{"id":"NF87.tsx","timestamp":1754180470172},{"id":"CmTP.tsx","timestamp":1754180493444},{"id":"E3En.tsx","source":"moved.source","sourceDescription":"~/codes/main-thera/src/app/components/Background.tsx","timestamp":1754183016450},{"id":"m1B0.tsx","source":"moved.source","sourceDescription":"~/codes/main-thera/src/components/Background.tsx","timestamp":1754183112421},{"id":"KKfz.tsx","source":"moved.source","sourceDescription":"~/codes/main-thera/src/app/components/Background.tsx","timestamp":1754191473300},{"id":"8E57.tsx","timestamp":1754196748903},{"id":"zH6B.tsx","timestamp":1754198926113},{"id":"m9eB.tsx","source":"undoRedo.source","timestamp":1754198929479},{"id":"ivRz.tsx","timestamp":1754198983177},{"id":"8lsH.tsx","timestamp":1754199040303},{"id":"PUwk.tsx","timestamp":1754199082884},{"id":"kK2l.tsx","timestamp":1754199135297},{"id":"0d84.tsx","timestamp":1754199335649},{"id":"rxpc.tsx","timestamp":1754199356949},{"id":"UPgV.tsx","timestamp":1754199390549},{"id":"RuXt.tsx","source":"undoRedo.source","timestamp":1754199402597},{"id":"Y7aQ.tsx","timestamp":1754199468873},{"id":"VwLY.tsx","timestamp":1754199499886},{"id":"T7nd.tsx","timestamp":1754199519073}]}