{"version":2,"sessionId":"1342152a-0505-455b-88ac-c8168e331185","linearHistory":[{"requestId":"request_1e24e06f-56e6-47ce-8284-681f449f7c3d","stops":[{"entries":[{"resource":"file:///home/monteiro/codes/Latex/main.tex","languageId":"latex","originalHash":"8fc179c","currentHash":"8fc179c","originalToCurrentEdit":[],"state":0,"snapshotUri":"chat-editing-snapshot-text-model:/home/monteiro/codes/Latex/main.tex?%7B%22sessionId%22%3A%221342152a-0505-455b-88ac-c8168e331185%22%2C%22requestId%22%3A%22request_1e24e06f-56e6-47ce-8284-681f449f7c3d%22%2C%22undoStop%22%3A%22%22%7D","telemetryInfo":{"requestId":"request_1e24e06f-56e6-47ce-8284-681f449f7c3d"}}]}],"postEdit":[{"resource":"file:///home/monteiro/codes/Latex/main.tex","languageId":"latex","originalHash":"8fc179c","currentHash":"cdb67a6","originalToCurrentEdit":[{"txt":"\\documentclass[","pos":0,"len":15},{"txt":"    12pt,","pos":16,"len":44},{"txt":"    openright,","pos":61,"len":44},{"txt":"    oneside,","pos":106,"len":72},{"txt":"    a4paper,","pos":179,"len":89},{"txt":"    english,    % secondary language","pos":269,"len":82},{"txt":"    brazil      % main language","pos":352,"len":60},{"txt":"]{abntex2}","pos":413,"len":35},{"txt":"","pos":449,"len":92},{"txt":"% --- PACOTES ---","pos":542,"len":70},{"txt":"% Pacotes para formatação ABNT","pos":613,"len":69},{"txt":"\\usepackage{abntex2cite}     % Estilos de citação e bibliografia ABNT","pos":683,"len":74},{"txt":"","pos":758,"len":93},{"txt":"% Pacotes essenciais","pos":852,"len":59},{"txt":"\\usepackage[T1]{fontenc}     % Codificação de fonte","pos":912,"len":10},{"txt":"\\usepackage[utf8]{inputenc}  % Codificação de entrada","pos":923,"len":0},{"txt":"\\usepackage{lmodern}         % Fonte Latin Modern (melhora a aparência)","pos":924,"len":17},{"txt":"\\usepackage{indentfirst}     % Indenta o primeiro parágrafo de cada seção","pos":942,"len":30},{"txt":"\\usepackage{color}           % Para cores","pos":973,"len":69},{"txt":"\\usepackage{graphicx}        % Para incluir imagens","pos":1043,"len":0},{"txt":"\\usepackage{lastpage}        % Para referências à última página","pos":1044,"len":20},{"txt":"","pos":1065,"len":53},{"txt":"% Pacotes para gráficos e tabelas","pos":1119,"len":51},{"txt":"\\usepackage{float}           % Para controlar a posição de figuras e tabelas","pos":1171,"len":71},{"txt":"\\usepackage{caption}         % Para legendas de figuras e tabelas","pos":1243,"len":54},{"txt":"\\usepackage{subcaption}      % Para subfiguras","pos":1298,"len":73},{"txt":"% Pacotes para matemática","pos":1373,"len":33},{"txt":"\\usepackage{amsmath, amsfonts, amssymb} % Pacotes matemáticos","pos":1407,"len":51},{"txt":"","pos":1459,"len":76},{"txt":"% Pacotes para links","pos":1536,"len":65},{"txt":"\\usepackage[hidelinks]{hyperref} % Para links clicáveis no PDF (hidelinks remove as caixas coloridas)","pos":1602,"len":46},{"txt":"% --- CONFIGURAÇÕES DE LAYOUT (ABNTEX2 já configura grande parte) ---","pos":1650,"len":25},{"txt":"% Ajustes finos de margens se necessário (abntex2 já tem defaults bons)","pos":1676,"len":61},{"txt":"% \\usepackage[a4paper, top=3cm, bottom=2cm, left=3cm, right=2cm]{geometry}","pos":1738,"len":0},{"txt":"","pos":1739,"len":20},{"txt":"","pos":1760,"len":101},{"txt":"% --- INFORMAÇÕES DO DOCUMENTO (PARA CAPA E FOLHA DE ROSTO) ---","pos":1862,"len":0},{"txt":"\\autor{Gabriel Silva Monteiro}","pos":1863,"len":69},{"txt":"\\titulo{Desenvolvimento de um Back-End para um Sistema Multiplataforma para a Empresa Júnior do Curso de Bacharelado em Engenharia de Computação da UEMA}","pos":1933,"len":71},{"txt":"\\local{São Luís - MA}","pos":2005,"len":74},{"txt":"\\data{\\today} % Ou defina a data específica se necessário","pos":2080,"len":0},{"txt":"\\orientador{Prof. Pedro Brandão Neto}","pos":2081,"len":0},{"txt":"\\instituicao{","pos":2082,"len":63},{"txt":"  Universidade Estadual do Maranhão -- UEMA \\\\","pos":2146,"len":30},{"txt":"  Centro de Ciências Tecnológicas -- CCT \\\\","pos":2177,"len":153},{"txt":"  Departamento de Engenharia de Computação","pos":2331,"len":21},{"txt":"}","pos":2353,"len":57},{"txt":"\\tipotrabalho{Relatório de Iniciação Científica}","pos":2411,"len":37},{"txt":"\\preambulo{Relatório parcial referente às atividades realizadas conforme o cronograma previsto no plano de trabalho da iniciação científica.}","pos":2449,"len":13},{"txt":"","pos":2463,"len":46},{"txt":"","pos":2510,"len":43},{"txt":"% --- INÍCIO DO DOCUMENTO ---","pos":2554,"len":42},{"txt":"\\begin{document}","pos":2597,"len":1},{"txt":"","pos":2599,"len":48},{"txt":"% Elementos pré-textuais (gerados pelo abntex2)","pos":2648,"len":141},{"txt":"\\imprimircapa           % Imprime a capa","pos":2790,"len":0},{"txt":"\\imprimirfolhaderosto    % Imprime a folha de rosto","pos":2791,"len":0},{"txt":"","pos":2792,"len":29},{"txt":"% Resumo e Palavras-chave","pos":2822,"len":16},{"txt":"% O abntex2 já tem comandos específicos para isso","pos":2839,"len":0},{"txt":"\\resumo{O objetivo deste trabalho é o desenvolvimento de um back-end para um sistema multiplataforma destinado à Technos, empresa júnior do curso de Bacharelado em Engenharia de Computação do Centro de Ciências Tecnológicas da Universidade Estadual do Maranhão. A Technos busca apoiar a formação dos alunos proporcionando o contato dos alunos com a prestação de serviços de hardware e software à comunidade interna e externa à universidade, com o treinamento em produtos tecnológicos, conserto e manutenção de equipamentos eletrônicos, com excelência de qualidade e baixo custo. Para a melhoria e organização da empresa é proposto um sistema multiplataforma para organização das demandas, registro dos materiais permanentes e de uso contínuo, cadastros de usuários e clientes, com a integração de vendas de serviços e apresentação da empresa. O trabalho deve pesquisar as melhores tecnologias de banco de dados, conexão interna do sistema, segurança da informação, escalabilidade e versatilidade para um sistema confiável, procurando garantir a confidencialidade, integridade e disponibilidade dos serviços a serem prestados.}","pos":2840,"len":47},{"txt":"","pos":2888,"len":40},{"txt":"\\palavraschave{Empresa júnior, sistema multiplataforma, back-end, serviços}","pos":2929,"len":51},{"txt":"\\begin{abstract}","pos":2982,"len":25},{"txt":"    O objetivo deste trabalho é o desenvolvimento de um back-end para um sistema multiplataforma destinado à Technos, empresa júnior do curso de Bacharelado em Engenharia de Computação do Centro de Ciências Tecnológicas da Universidade Estadual do Maranhão. A Technos busca apoiar a formação dos alunos proporcionando o contato dos alunos com a prestação de serviços de hardware e software à comunidade interna e externa à universidade, com o treinamento em produtos tecnológicos, conserto e manutenção de equipamentos eletrônicos, com excelência de qualidade e baixo custo. Para a melhoria e organização da empresa é proposto um sistema multiplataforma para organização das demandas, registro dos materiais permanentes e de uso contínuo, cadastros de usuários e clientes, com a integração de vendas de serviços e apresentação da empresa. O trabalho deve pesquisar as melhores tecnologias de banco de dados, conexão interna do sistema, segurança da informação, escalabilidade e versatilidade para um sistema confiável, procurando garantir a confidencialidade, integridade e disponibilidade dos serviços a serem prestados.","pos":3008,"len":49},{"txt":"\\end{abstract}","pos":3058,"len":1126},{"txt":"\\keywords{Junior enterprise. Multiplatform system. Back-end. Services.}","pos":4186,"len":75},{"txt":"% Listas (abntex2 já inclui os comandos)","pos":4263,"len":40},{"txt":"\\listoffigures         % Lista de figuras","pos":4304,"len":41},{"txt":"% \\listoftables          % Lista de tabelas (comente se não tiver tabelas)","pos":4346,"len":74},{"txt":"\\sumario               % Gera o sumário (abntex2 tem seu próprio sumário)","pos":4422,"len":73},{"txt":"% --- ELEMENTOS TEXTUAIS ---","pos":4497,"len":28},{"txt":"\\textual               % Comando do abntex2 para iniciar a numeração das páginas","pos":4526,"len":80},{"txt":"\\section{Introdução}","pos":4608,"len":20},{"txt":"\\input{secoes/introducao.tex}","pos":4629,"len":29},{"txt":"\\section{Objetivos}","pos":4660,"len":19},{"txt":"\\input{secoes/objetivos.tex}","pos":4680,"len":28},{"txt":"\\section{Metodologia}","pos":4710,"len":21},{"txt":"\\input{secoes/metodologia.tex}","pos":4732,"len":30},{"txt":"\\section{Resultados} % Renomeei para \"Resultados\" conforme seu documento original, que usa \"Resultados Parciais\"","pos":4764,"len":112},{"txt":"\\input{secoes/resultados.tex}","pos":4877,"len":29},{"txt":"\\section{Considerações Parciais} % Mudei para \"Considerações Parciais\" conforme o texto do seu documento","pos":4908,"len":104},{"txt":"\\input{secoes/consideracoes_parciais.tex}","pos":5013,"len":41},{"txt":"% --- ELEMENTOS PÓS-TEXTUAIS ---","pos":5056,"len":32},{"txt":"% O abntex2 gerencia as referências automaticamente com \\bibliography","pos":5089,"len":69},{"txt":"\\bibliography{referencias} % Onde 'referencias.bib' é o nome do seu arquivo .bib","pos":5159,"len":80},{"txt":"\\end{document}","pos":5241,"len":14}],"state":0,"snapshotUri":"chat-editing-snapshot-text-model:/home/monteiro/codes/Latex/main.tex?%7B%22sessionId%22%3A%221342152a-0505-455b-88ac-c8168e331185%22%2C%22requestId%22%3A%22request_1e24e06f-56e6-47ce-8284-681f449f7c3d%22%2C%22undoStop%22%3A%22d19944f6-f46c-4e17-911b-79a8e843c7c0%22%7D","telemetryInfo":{"requestId":"request_1e24e06f-56e6-47ce-8284-681f449f7c3d"}}]}],"linearHistoryIndex":1,"initialFileContents":[["file:///home/monteiro/codes/Latex/main.tex","8fc179c"]],"recentSnapshot":{"entries":[{"resource":"file:///home/monteiro/codes/Latex/main.tex","languageId":"latex","originalHash":"8fc179c","currentHash":"cdb67a6","originalToCurrentEdit":[{"txt":"\n    openright,\n    oneside,\n    a4paper,\n    english,    % secondary language\n    brazil      % main language\n","pos":25,"len":887},{"txt":"\\usepackage[T1]{fontenc}     % Codificação de fonte\n","pos":1065,"len":0},{"txt":"","pos":1119,"len":52},{"txt":"","pos":1243,"len":55},{"txt":"\\usepackage{color}           % Para cores\n\\usepackage{graphicx}        % Para incluir imagens\n\\usepackage{lastpage}        % Para referências à última página\n","pos":1372,"len":0},{"txt":"","pos":1407,"len":52},{"txt":"\n\\begin{abstract}\n    O objetivo deste trabalho é o desenvolvimento de um back-end para um sistema multiplataforma destinado à Technos, empresa júnior do curso de Bacharelado em Engenharia de Computação do Centro de Ciências Tecnológicas da Universidade Estadual do Maranhão. A Technos busca apoiar a formação dos alunos proporcionando o contato dos alunos com a prestação de serviços de hardware e software à comunidade interna e externa à universidade, com o treinamento em produtos tecnológicos, conserto e manutenção de equipamentos eletrônicos, com excelência de qualidade e baixo custo. Para a melhoria e organização da empresa é proposto um sistema multiplataforma para organização das demandas, registro dos materiais permanentes e de uso contínuo, cadastros de usuários e clientes, com a integração de vendas de serviços e apresentação da empresa. O trabalho deve pesquisar as melhores tecnologias de banco de dados, conexão interna do sistema, segurança da informação, escalabilidade e versatilidade para um sistema confiável, procurando garantir a confidencialidade, integridade e disponibilidade dos serviços a serem prestados.\n\\end{abstract}\n\n\\keywords{Junior enterprise. Multiplatform system. Back-end. Services.}\n","pos":4262,"len":0}],"state":0,"snapshotUri":"chat-editing-snapshot-text-model:/home/monteiro/codes/Latex/main.tex?%7B%22sessionId%22%3A%221342152a-0505-455b-88ac-c8168e331185%22%2C%22requestId%22%3A%22%22%2C%22undoStop%22%3A%22%22%7D","telemetryInfo":{"requestId":"request_1e24e06f-56e6-47ce-8284-681f449f7c3d"}}]}}